MANIFEST.in
README.md
requirements.txt
setup.cfg
setup.py
napalm_iosxr_grpc/__init__.py
napalm_iosxr_grpc/xrgrpc.py
napalm_iosxr_grpc.egg-info/PKG-INFO
napalm_iosxr_grpc.egg-info/SOURCES.txt
napalm_iosxr_grpc.egg-info/dependency_links.txt
napalm_iosxr_grpc.egg-info/requires.txt
napalm_iosxr_grpc.egg-info/top_level.txt